libreda_python-0.0.4.dist-info/METADATA
libreda_python-0.0.4.dist-info/WHEEL
libreda/__init__.py
libreda/libreda.cpython-311-x86_64-linux-gnu.so
libreda_python-0.0.4.dist-info/RECORD
