Metadata-Version: 2.1
Name: libreda-python
Version: 0.0.4
Summary: Python binding for the LibrEDA database.
Keywords: vlsi,python
Home-Page: https://libreda.org
Author: Thomas Kramer <code@tkramer.ch>
Author-email: Thomas Kramer <code@tkramer.ch>
License: AGPL-3.0-or-later
Project-URL: Source Code, https://codeberg.org/libreda/libreda-python
